mt_BulkAddAsset/__init__.py
mt_BulkAddAsset/mt_BulkAddAsset.py
mt_BulkAddAsset/UI/MaxTrack_Main.ui
mt_BulkAddAsset/UI/MaxTrack_Main1.ui
mt_BulkAddAsset-0.1.1.dist-info/LICENSE
mt_BulkAddAsset-0.1.1.dist-info/METADATA
mt_BulkAddAsset-0.1.1.dist-info/WHEEL
mt_BulkAddAsset-0.1.1.dist-info/top_level.txt
mt_BulkAddAsset-0.1.1.dist-info/RECORD
