Metadata-Version: 2.1
Name: mt-BulkAddAsset
Version: 0.1.1
Summary: A package for adding assets to Met/Track
Home-page: UNKNOWN
Author: mole1000
Author-email: mole1000@protonmail.com
License: UNKNOWN
Platform: UNKNOWN
Classifier: Programming Language :: Python :: 3
Classifier: License :: OSI Approved :: MIT License
Classifier: Operating System :: OS Independent
Requires-Python: >=3.6
Requires-Dist: PyQt5 (>=5)
Requires-Dist: mt-FileMan (>=0.0.3)
Requires-Dist: mt-UI (>=0.0.2)
Provides-Extra: testing
Requires-Dist: pytest ; extra == 'testing'
